dsnd_distributions_yh/Binomialdistribution.py
dsnd_distributions_yh/Gaussiandistribution.py
dsnd_distributions_yh/Generaldistribution.py
dsnd_distributions_yh/__init__.py
dsnd_distributions_yh-0.1.dist-info/LICENSE
dsnd_distributions_yh-0.1.dist-info/METADATA
dsnd_distributions_yh-0.1.dist-info/WHEEL
dsnd_distributions_yh-0.1.dist-info/top_level.txt
dsnd_distributions_yh-0.1.dist-info/RECORD
